Workbook

Sheet 测试用例清单
A1: LocalLife Copilot 测试用例清单 | K1: LocalLife Copilot 测试用例清单（2026-07-26 实际执行版）
A2: 基于当前工作区、17个 Story 与项目原生自动化资产执行；本次结果：48通过、1阻塞（MODEL-04实际训练产物）。 | K2: 自动化证据、测试代码、执行结果、缺陷与备注
A3: 用例总数 | B3: =COUNTA(A7:A55) | D3: P0 数量 | E3: =COUNTIF(E7:E55,"P0") | G3: P1 数量 | H3: =COUNTIF(E7:E55,"P1") | J3: 已通过 | K3: =COUNTIF(N7:N55,"通过") | M3: 阻断/失败 | N3: =COUNTIF(N7:N55,"失败")+COUNTIF(N7:N55,"阻塞")
A4: 历史报告仅作为既有证据；最终签署必须绑定发布候选 Commit，并补齐真实性能样本。 | K4: 执行结果由测试人员回填；失败/阻塞必须关联缺陷与证据。
A6: 用例ID | B6: Epic | C6: Story | D6: 模块 | E6: 优先级 | F6: 测试类型 | G6: 前置条件 | H6: 测试需求 | I6: 测试步骤/重点 | J6: 预期结果 | K6: 自动化状态 | L6: 现有测试证据 | M6: 新增测试代码 | N6: 执行结果 | O6: 缺陷编号 | P6: 备注
A7: AUTH-01 | B7: EP-01 | C7: ST-101 | D7: 认证、治理与资源权限 | E7: P0 | F7: 功能/集成 | G7: API 已启动；准备普通用户、商家与管理角色账号；MySQL/Redis 可用 | H7: 正确账号登录与角色分流 | I7: 使用普通用户、商家角色、管理角色分别登录；检查 /api/v1/auth/login、/users/me 及前端工作台跳转。 | J7: 返回 Access/Refresh Token；用户信息含角色与授权范围；进入 /app、/merchant 或 /admin 对应工作台。 | K7: 已执行自动化验证 | L7: backend/tests/test_auth.py；test_authorization.py；test_login_rate_limit.py；frontend/src/router、stores/auth 测试 | M7: test_code/test_release_candidate_smoke.py | N7: 通过 | P7: AUTH 分组、黑盒冒烟及 MySQL 认证/授权集成均通过；见 functional/01~02、acceptance/03、full-validation/05。
A8: AUTH-02 | B8: EP-01 | C8: ST-101 | D8: 认证、治理与资源权限 | E8: P0 | F8: 安全/异常 | G8: API 已启动；准备普通用户、商家与管理角色账号；MySQL/Redis 可用 | H8: 错误凭据与账号信息保护 | I8: 提交错误密码、未知账号和空字段；检查统一错误契约与日志。 | J8: 错误凭据返回 401；空字段返回 422；响应和日志不泄露账号是否存在、密码或 Token。 | K8: 已执行自动化验证 | L8: backend/tests/test_auth.py；test_authorization.py；test_login_rate_limit.py；frontend/src/router、stores/auth 测试 | M8: test_code/test_release_candidate_smoke.py | N8: 通过 | P8: AUTH 分组、黑盒冒烟及 MySQL 认证/授权集成均通过；见 functional/01~02、acceptance/03、full-validation/05。
A9: AUTH-03 | B9: EP-01 | C9: ST-101 | D9: 认证、治理与资源权限 | E9: P0 | F9: 安全/异常 | G9: API 已启动；准备普通用户、商家与管理角色账号；MySQL/Redis 可用 | H9: 登录失败限流 | I9: 同一规范化账号与客户端 IP 连续失败至阈值并继续请求；随后等待窗口或成功登录。 | J9: 达到阈值返回 429、AUTH_RATE_LIMITED 与 Retry-After；键中不存原始账号/IP；窗口后或成功登录可清零。 | K9: 已执行自动化验证 | L9: backend/tests/test_auth.py；test_authorization.py；test_login_rate_limit.py；frontend/src/router、stores/auth 测试 | M9: test_code/run_project_test_cases.py（调用项目原生自动化证据） | N9: 通过 | P9: AUTH 分组、黑盒冒烟及 MySQL 认证/授权集成均通过；见 functional/01~02、acceptance/03、full-validation/05。
A10: AUTH-04 | B10: EP-01 | C10: ST-101 | D10: 认证、治理与资源权限 | E10: P0 | F10: 安全/异常 | G10: API 已启动；准备普通用户、商家与管理角色账号；MySQL/Redis 可用 | H10: Refresh Token 轮换与重放 | I10: 用有效 Refresh Token 刷新，再并发或重复提交旧 Token。 | J10: 新令牌对签发；旧 Refresh Token 立即失效；重放返回 401 且不会产生第二个有效会话。 | K10: 已执行自动化验证 | L10: backend/tests/test_auth.py；test_authorization.py；test_login_rate_limit.py；frontend/src/router、stores/auth 测试 | M10: test_code/test_release_candidate_smoke.py | N10: 通过 | P10: AUTH 分组、黑盒冒烟及 MySQL 认证/授权集成均通过；见 functional/01~02、acceptance/03、full-validation/05。
A11: AUTH-05 | B11: EP-01 | C11: ST-101 | D11: 认证、治理与资源权限 | E11: P0 | F11: 安全/异常 | G11: API 已启动；准备普通用户、商家与管理角色账号；MySQL/Redis 可用 | H11: 退出与 Access Token 撤销 | I11: 登录后调用 logout，再使用原 Access/Refresh Token 访问受保护接口。 | J11: 退出成功；原令牌不可再次使用；撤销记录与审计可追踪。 | K11: 已执行自动化验证 | L11: backend/tests/test_auth.py；test_authorization.py；test_login_rate_limit.py；frontend/src/router、stores/auth 测试 | M11: test_code/run_project_test_cases.py（调用项目原生自动化证据） | N11: 通过 | P11: AUTH 分组、黑盒冒烟及 MySQL 认证/授权集成均通过；见 functional/01~02、acceptance/03、full-validation/05。
A12: AUTH-06 | B12: EP-01 | C12: ST-101 | D12: 认证、治理与资源权限 | E12: P0 | F12: 安全/异常 | G12: API 已启动；准备普通用户、商家与管理角色账号；MySQL/Redis 可用 | H12: 角色与资源横向越权 | I12: 普通用户访问管理接口；商家 A 访问商家 B；知识库管理员访问未授权知识库；尝试直接拼接资源 ID。 | J12: 角色不足返回 403；不可见资源按契约返回 404/403；Repository 查询同样过滤，响应不泄露目标资源信息。 | K12: 已执行自动化验证 | L12: backend/tests/test_auth.py；test_authorization.py；test_login_rate_limit.py；frontend/src/router、stores/auth 测试 | M12: test_code/test_release_candidate_smoke.py | N12: 通过 | P12: AUTH 分组、黑盒冒烟及 MySQL 认证/授权集成均通过；见 functional/01~02、acceptance/03、full-validation/05。
A13: GOV-01 | B13: EP-01 | C13: ST-103 | D13: 认证、治理与资源权限 | E13: P1 | F13: 安全/异常 | G13: 平台管理员已登录；治理版本、敏感规则、结构化日志和审计存储可用 | H13: 配置版本、敏感规则、日志与审计闭环 | I13: 创建提示词/模型配置新版本并尝试原地修改；触发输入与输出敏感规则；执行发布、回滚和失败操作后按用户、模块、时间与结果查询日志和审计。 | J13: 已发布正文不可原地修改；敏感输入被阻断或拒答、敏感输出停止返回；JSON 日志含 request_id/user_id/conversation_id/latency_ms 且不含密码、Token 或密钥；审计只增可筛选并记录操作者、版本、时间和结果。 | K13: 已执行自动化验证 | L13: backend/tests/test_config.py；test_observability.py；test_governance_versions.py；test_governance_safety.py；test_governance_api.py | M13: test_code/run_project_test_cases.py（调用项目原生自动化证据） | N13: 通过 | P13: 治理分组通过，ST-103 两条真实 MySQL 并发用例已启用通过；见 functional/05、full-validation/05。
A14: KB-01 | B14: EP-01 | C14: ST-102 | D14: 知识库、文档与任务 | E14: P0 | F14: 功能/集成 | G14: 管理员已登录；MySQL、Redis、OpenSearch、Worker healthy；准备六类样例文件 | H14: 知识库创建、查询与编辑 | I14: 创建知识库；按名称/状态分页查询；读取详情并修改名称、描述或授权配置。 | J14: 响应符合统一契约；列表统计与详情一致；版本/审计字段更新；未授权资源不可见。 | K14: 已执行自动化验证 | L14: backend/tests/test_knowledge_service.py；test_file_loaders.py；test_ingestion_acceptance.py；test_security_upload.py；test_task_*；test_search_indexes.py | M14: test_code/run_project_test_cases.py（调用项目原生自动化证据） | N14: 通过 | P14: 知识库后端 76 条、前端 9 条及 ST-102 MySQL/Redis 集成通过；见 functional/03~04、full-validation/05。
A15: KB-02 | B15: EP-02 | C15: ST-201 | D15: 知识库、文档与任务 | E15: P0 | F15: 功能/集成 | G15: 管理员已登录；MySQL、Redis、OpenSearch、Worker healthy；准备六类样例文件 | H15: 六类文档上传与索引 | I15: 分别上传 PDF、DOCX、MD、TXT、CSV、XLSX；轮询返回 task_id。 | J15: 均生成标准记录、版本和 Chunk；任务最终 SUCCEEDED；内容、metadata、source_key、hash 可追溯。 | K15: 已执行自动化验证 | L15: backend/tests/test_knowledge_service.py；test_file_loaders.py；test_ingestion_acceptance.py；test_security_upload.py；test_task_*；test_search_indexes.py | M15: test_code/run_project_test_cases.py（调用项目原生自动化证据） | N15: 通过 | P15: 知识库后端 76 条、前端 9 条及 ST-102 MySQL/Redis 集成通过；见 functional/03~04、full-validation/05。
A16: KB-03 | B16: EP-02 | C16: ST-201 | D16: 知识库、文档与任务 | E16: P0 | F16: 安全/异常 | G16: 管理员已登录；MySQL、Redis、OpenSearch、Worker healthy；准备六类样例文件 | H16: 恶意与非法文件拦截 | I16: 覆盖路径穿越、伪造扩展名/MIME/签名、宏/可执行载荷、压缩炸弹、超限大小/数量。 | J16: 建档和写盘前拒绝；返回明确 4xx 错误码；不产生残留文件、文档版本、任务或可执行内容。 | K16: 已执行自动化验证 | L16: backend/tests/test_knowledge_service.py；test_file_loaders.py；test_ingestion_acceptance.py；test_security_upload.py；test_task_*；test_search_indexes.py | M16: test_code/run_project_test_cases.py（调用项目原生自动化证据） | N16: 通过 | P16: 知识库后端 76 条、前端 9 条及 ST-102 MySQL/Redis 集成通过；见 functional/03~04、full-validation/05。
A17: KB-04 | B17: EP-02 | C17: ST-201 | D17: 知识库、文档与任务 | E17: P0 | F17: 功能/集成 | G17: 管理员已登录；MySQL、Redis、OpenSearch、Worker healthy；准备六类样例文件 | H17: 重复导入与幂等投影 | I17: 对同一文件重复上传或重复消费同一 Outbox 事件；比较文档 hash、Chunk ID 与索引数量。 | J17: 不产生重复有效版本/Chunk；稳定 ID 保持一致；MySQL 与 OpenSearch 数量和内容一致。 | K17: 已执行自动化验证 | L17: backend/tests/test_knowledge_service.py；test_file_loaders.py；test_ingestion_acceptance.py；test_security_upload.py；test_task_*；test_search_indexes.py | M17: test_code/run_project_test_cases.py（调用项目原生自动化证据） | N17: 通过 | P17: 知识库后端 76 条、前端 9 条及 ST-102 MySQL/Redis 集成通过；见 functional/03~04、full-validation/05。
A18: KB-05 | B18: EP-01 | C18: ST-102 | D18: 知识库、文档与任务 | E18: P1 | F18: 功能/集成 | G18: 管理员已登录；MySQL、Redis、OpenSearch、Worker healthy；准备六类样例文件 | H18: 异步任务进度、取消与重试 | I18: 查询任务阶段/进度；在可取消阶段取消；构造失败任务并重试；对不可中断阶段发起取消。 | J18: 状态机转换合法；失败显示 error_code/stage；可重试任务产生受控重试；不可取消时返回 409。 | K18: 已执行自动化验证 | L18: backend/tests/test_knowledge_service.py；test_file_loaders.py；test_ingestion_acceptance.py；test_security_upload.py；test_task_*；test_search_indexes.py | M18: test_code/run_project_test_cases.py（调用项目原生自动化证据） | N18: 通过 | P18: 知识库后端 76 条、前端 9 条及 ST-102 MySQL/Redis 集成通过；见 functional/03~04、full-validation/05。
... A37: MODEL-03 | B37: EP-05 | C37: ST-501 | D37: 反馈、数据集与模型治理 | E37: P0 | F37: 功能/集成 | G37: 反馈/数据集/模型管理权限就绪；训练或评测依赖按用例准备 | H37: 不可变数据集与隔离切分 | I37: 生成 JSONL 后校验 SHA-256；尝试修改；检查 train/validation/test 的实体或会话交集。 | J37: 数据集不可原地修改；hash、样本量、来源可追溯；切分无会话/实体泄漏和重复。 | K37: 已执行自动化验证 | L37: backend/tests/test_feedback_*；test_dataset_builder.py；test_train_lora.py；test_governance_*；前端模型/反馈组件测试 | M37: test_code/run_project_test_cases.py（调用项目原生自动化证据） | N37: 通过 | P37: 模型治理后端 202 条、前端 10 条通过；见 functional/14~15。
A38: MODEL-04 | B38: EP-05 | C38: ST-502 | D38: 反馈、数据集与模型治理 | E38: P1 | F38: 功能/集成 | G38: 反馈/数据集/模型管理权限就绪；训练或评测依赖按用例准备 | H38: LoRA 可复现训练与产物完整性 | I38: 固定代码、基础模型 revision、数据集 hash、随机种子和超参数运行 CPU smoke/正式训练。 | J38: 生成日志、checkpoint、adapter、tokenizer 配置和 SHA-256；同配置关键指标在允许误差内复现。 | K38: 已执行自动化验证 | L38: backend/tests/test_feedback_*；test_dataset_builder.py；test_train_lora.py；test_governance_*；前端模型/反馈组件测试 | M38: test_code/run_project_test_cases.py（调用项目原生自动化证据） | N38: 阻塞 | O38: BLOCK-MODEL-ARTIFACT-001 | P38: 训练配置/任务逻辑自动化已通过，但 33 条实际产物校验因缺少 smoke-001、smoke-002、lora-001 及 peft/datasets/accelerate 而跳过；需完成两次 smoke 与一次正式 LoRA 训练后复跑 test_train_lora_artifacts.py。
A39: MODEL-05 | B39: EP-05 | C39: ST-502 | D39: 反馈、数据集与模型治理 | E39: P0 | F39: 功能/集成 | G39: 反馈/数据集/模型管理权限就绪；训练或评测依赖按用例准备 | H39: 仅 APPROVED 模型可部署 | I39: 对 DRAFT、EVALUATING、REJECTED、APPROVED 状态分别发起部署。 | J39: 仅 APPROVED 成功；非法状态返回 409；所有尝试记录操作者、版本、时间和结果。 | K39: 已执行自动化验证 | L39: backend/tests/test_feedback_*；test_dataset_builder.py；test_train_lora.py；test_governance_*；前端模型/反馈组件测试 | M39: test_code/run_project_test_cases.py（调用项目原生自动化证据） | N39: 通过 | P39: 模型治理后端 202 条、前端 10 条通过；见 functional/14~15。
A40: MODEL-06 | B40: EP-05 | C40: ST-502 | D40: 反馈、数据集与模型治理 | E40: P0 | F40: 功能/集成 | G40: 反馈/数据集/模型管理权限就绪；训练或评测依赖按用例准备 | H40: 灰度比例与单一全量 ACTIVE | I40: 设置 0、边界、超 100 的灰度比例；并发发布两个全量版本。 | J40: 比例校验生效；同一场景灰度总量不超 100；最多一个全量 ACTIVE，冲突失败关闭。 | K40: 已执行自动化验证 | L40: backend/tests/test_feedback_*；test_dataset_builder.py；test_train_lora.py；test_governance_*；前端模型/反馈组件测试 | M40: test_code/run_project_test_cases.py（调用项目原生自动化证据） | N40: 通过 | P40: 模型治理后端 202 条、前端 10 条通过；见 functional/14~15。
A41: MODEL-07 | B41: EP-05 | C41: ST-502 | D41: 反馈、数据集与模型治理 | E41: P0 | F41: 功能/集成 | G41: 反馈/数据集/模型管理权限就绪；训练或评测依赖按用例准备 | H41: 模型回滚与路由切换审计 | I41: 从当前活动版本回滚上一稳定版本；发起新请求并查询部署/审计记录。 | J41: 新请求路由到稳定版本；旧请求不被篡改；产生 ROLLBACK 审计；失败回滚保持原活动版本。 | K41: 已执行自动化验证 | L41: backend/tests/test_feedback_*；test_dataset_builder.py；test_train_lora.py；test_governance_*；前端模型/反馈组件测试 | M41: test_code/run_project_test_cases.py（调用项目原生自动化证据） | N41: 通过 | P41: 模型治理后端 202 条、前端 10 条通过；见 functional/14~15。
A42: UI-01 | B42: EP-06 | C42: ST-601 | D42: 前端路由、管理与体验 | E42: P0 | F42: 功能/集成 | G42: 前端与 API 可访问；准备游客及各角色会话；Chromium 可用 | H42: 游客只读发现页 | I42: 清空令牌访问 /；尝试进入 /app/reviews、/merchant、/admin。 | J42: 发现页可只读；受保护路由跳转登录并保留安全 redirect；不能通过前端直达获得数据。 | K42: 已执行自动化验证 | L42: frontend/src/router、utils、responsive-layout.test.ts；frontend/e2e/responsive-user-workspace.spec.ts | M42: test_code/run_project_test_cases.py（调用项目原生自动化证据） | N42: 通过 | P42: UI 单元 12 条、响应式 Playwright 2 条及全量前端 136 条通过；见 functional/16~17、full-validation/02。
A43: UI-02 | B43: EP-06 | C43: ST-601 | D43: 前端路由、管理与体验 | E43: P0 | F43: 功能/集成 | G43: 前端与 API 可访问；准备游客及各角色会话；Chromium 可用 | H43: 角色路由守卫与安全重定向 | I43: 分别使用 USER、MERCHANT、各 ADMIN 角色访问所有页面；传入 //evil 或外部 redirect。 | J43: 角色进入正确工作台；无权页面回到角色主页；只接受站内单斜杠路径，阻断开放重定向。 | K43: 已执行自动化验证 | L43: frontend/src/router、utils、responsive-layout.test.ts；frontend/e2e/responsive-user-workspace.spec.ts | M43: test_code/run_project_test_cases.py（调用项目原生自动化证据） | N43: 通过 | P43: UI 单元 12 条、响应式 Playwright 2 条及全量前端 136 条通过；见 functional/16~17、full-validation/02。
A44: UI-03 | B44: EP-06 | C44: ST-601 | D44: 前端路由、管理与体验 | E44: P1 | F44: 兼容/响应式 | G44: 前端与 API 可访问；准备游客及各角色会话；Chromium 可用 | H44: 桌面与移动端核心流程 | I44: 在 1440×900、1024×768、390×844 视口执行登录、对话、上传、图表和任务操作。 | J44: 无横向溢出、遮挡、重叠或不可点击控件；表格/图表可读；核心命令在首屏或可预测位置。 | K44: 已执行自动化验证 | L44: frontend/src/router、utils、responsive-layout.test.ts；frontend/e2e/responsive-user-workspace.spec.ts | M44: test_code/run_project_test_cases.py（调用项目原生自动化证据） | N44: 通过 | P44: UI 单元 12 条、响应式 Playwright 2 条及全量前端 136 条通过；见 functional/16~17、full-validation/02。
A45: UI-04 | B45: EP-06 | C45: ST-601 | D45: 前端路由、管理与体验 | E45: P0 | F45: 安全/异常 | G45: 前端与 API 可访问；准备游客及各角色会话；Chromium 可用 | H45: Markdown 与引用内容安全 | I45: 返回脚本、事件属性、javascript URL、恶意 HTML、超长链接和正常 Markdown。 | J45: 原始 HTML/脚本不执行；危险 URL 被移除；正常列表、代码和引用可读；来源跳转仍受控。 | K45: 已执行自动化验证 | L45: frontend/src/router、utils、responsive-layout.test.ts；frontend/e2e/responsive-user-workspace.spec.ts | M45: test_code/run_project_test_cases.py（调用项目原生自动化证据） | N45: 通过 | P45: UI 单元 12 条、响应式 Playwright 2 条及全量前端 136 条通过；见 functional/16~17、full-validation/02。
A46: UI-05 | B46: EP-06 | C46: ST-601 | D46: 前端路由、管理与体验 | E46: P1 | F46: 功能/集成 | G46: 前端与 API 可访问；准备游客及各角色会话；Chromium 可用 | H46: Token 刷新、服务不可用与恢复 | I46: 模拟 Token 临期、刷新失败、API 503、WebSocket 断开和恢复。 | J46: 临期自动刷新；失败清理会话并回登录；依赖故障展示服务不可用页；恢复后可重试且不重复提交。 | K46: 已执行自动化验证 | L46: frontend/src/router、utils、responsive-layout.test.ts；frontend/e2e/responsive-user-workspace.spec.ts | M46: test_code/run_project_test_cases.py（调用项目原生自动化证据） | N46: 通过 | P46: UI 单元 12 条、响应式 Playwright 2 条及全量前端 136 条通过；见 functional/16~17、full-validation/02。
A47: ADMIN-01 | B47: EP-06 | C47: ST-602 | D47: 前端路由、管理与体验 | E47: P1 | F47: 功能/集成 | G47: 知识库管理员已登录；知识库、文档、异步任务与检索调试数据就绪 | H47: 知识库管理与任务追踪完整体验 | I47: 在管理端执行知识库分页/筛选/编辑、批量上传前校验、文档与 Chunk 预览、版本回滚、任务进度/取消/失败重试及检索调试；再以无授权账号直达页面和接口。 | J47: 列表与详情统计一致；上传校验和逐文件/总进度清晰；危险操作二次确认；失败任务显示错误码、阶段和可重试入口；检索调试展示过滤、双路得分、融合排序与引用；无授权页面不可见且接口返回 403。 | K47: 已执行自动化验证 | L47: frontend/src/views/admin/KnowledgeBase*View.test.ts；DocumentUploadPanel、KnowledgeDocumentWorkspace、TaskProgressCard 与对应 API 测试 | M47: test_code/run_project_test_cases.py（调用项目原生自动化证据） | N47: 通过 | P47: 管理端 25 条及管理员上传/失败重试 E2E 通过；见 functional/18、acceptance/02。
A48: OPS-01 | B48: EP-07 | C48: ST-701 | D48: 部署、质量、验收与恢复 | E48: P0 | F48: 功能/集成 | G48: 发布候选 Commit 固定；按用例准备完整 Compose、备份或压测环境 | H48: 全新环境一键启动 | I48: 复制安全环境配置，在空业务卷执行 docker compose up --build --wait。 | J48: migrate→init→seed→api/worker 顺序正确；常驻服务 healthy；一次性任务 Exited(0)；确定性数据可用。 | K48: 已执行自动化验证 | L48: compose.yaml；.github/workflows/ci.yml；test_health.py；test_observability.py；test_storage_recovery.py；test_performance_gate.py；专项脚本 | M48: test_code/run_project_test_cases.py（调用项目原生自动化证据） | N48: 通过 | P48: Compose、运维单元、黑盒冒烟均通过；见 functional/19~21、acceptance/03。
A49: OPS-02 | B49: EP-07 | C49: ST-701 | D49: 部署、质量、验收与恢复 | E49: P0 | F49: 功能/集成 | G49: 发布候选 Commit 固定；按用例准备完整 Compose、备份或压测环境 | H49: 存活/就绪与依赖故障 | I49: 访问 /health/live、/health/ready；分别中断 MySQL、Redis、OpenSearch、模型网关。 | J49: live 仅反映进程；ready 并行检查依赖，任一失败返回 503 和逐项状态；恢复后重新 ready。 | K49: 已执行自动化验证 | L49: compose.yaml；.github/workflows/ci.yml；test_health.py；test_observability.py；test_storage_recovery.py；test_performance_gate.py；专项脚本 | M49: test_code/test_release_candidate_smoke.py | N49: 通过 | P49: Compose、运维单元、黑盒冒烟均通过；见 functional/19~21、acceptance/03。
A50: OPS-03 | B50: EP-07 | C50: ST-701 | D50: 部署、质量、验收与恢复 | E50: P0 | F50: 协议/集成 | G50: 发布候选 Commit 固定；按用例准备完整 Compose、备份或压测环境 | H50: Nginx 代理 REST/SSE/WebSocket | I50: 经 3000 入口调用 REST、长 SSE 和 WebSocket；检查 Upgrade、超时、缓存与响应缓冲。 | J50: 三类协议正常；SSE 数据帧及时到达且不缓存/缓冲；WebSocket 升级成功；安全头和错误契约保留。 | K50: 已执行自动化验证 | L50: compose.yaml；.github/workflows/ci.yml；test_health.py；test_observability.py；test_storage_recovery.py；test_performance_gate.py；专项脚本 | M50: test_code/test_release_candidate_smoke.py | N50: 通过 | P50: Compose、运维单元、黑盒冒烟均通过；见 functional/19~21、acceptance/03。
... A55: E2E-01 | B55: EP-07 | C55: ST-702 | D55: 部署、质量、验收与恢复 | E55: P0 | F55: 功能/集成 | G55: 发布候选 Commit 固定；空业务数据环境可初始化；Chromium 与完整 Compose 可用 | H55: 确定性数据与全角色核心链路三轮验收 | I55: 清空业务数据后重新初始化固定用户、角色、商家、点评、知识文档和问题集；运行管理员上传与索引、用户探店与引用、商家趋势、反馈、评测与模型回滚，并覆盖越权、无结果兜底和任务失败；在全新环境连续执行三轮。 | J55: 初始化结果稳定可重复；核心正向与错误链路全部通过；三轮结果一致；报告绑定环境、Commit、用例与结果，失败时保留截图/日志；演示脚本、时长、备用数据、模型降级方案和交付清单齐全。 | K55: 已执行自动化验证 | L55: backend/tests/test_seed_demo_data.py；test_seed_merchant_data.py；frontend/e2e/st-702-core-flows.spec.ts；ST-702 验收报告 | M55: test_code/run_project_test_cases.py（调用项目原生自动化证据） | N55: 通过 | P55: 确定性种子 11 条、桌面/移动核心角色链路 8 条通过；当前轮结果见 acceptance/，三轮全新环境沿用历史 TK-702-03 证据。

Sheet 本次执行结果
A1: LocalLife Copilot 本次完整执行结果
A2: 执行日期 | B2: 2026-07-26 | C2: 分支 | D2: main | E2: Commit | F2: 29b85eec13e27d958005c5952508b976c8241f70
A3: 工作区 | B3: 存在 14 项未提交改动 | C3: 用例结论 | D3: 48通过 / 1阻塞 | E3: 发布结论 | F3: 有条件通过
A5: 检查项 | B5: 结果 | C5: 通过/总数 | D5: 跳过 | E5: 关键指标 | F5: 证据位置
A6: 49条测试用例 | B6: 有条件通过 | C6: 48/49 | D6: 0 | E6: MODEL-04 阻塞 | F6: 测试用例清单
A7: 功能/治理/运维分组 | B7: PASS | C7: 22/22 | D7: 0 | E7: 22个命令级检查全通过 | F7: execution_results/2026-07-26-current/functional/
A8: 后端全量 pytest | B8: PASS | C8: 1191/1232 | D8: 41 | E8: 启用集成后另有19条通过 | F8: execution_results/2026-07-26-current/full-validation/
A9: 前端全量 Vitest | B9: PASS | C9: 136/136 | D9: 0 | E9: 38个文件、136条测试 | F9: execution_results/2026-07-26-current/full-validation/
A10: MySQL/Redis 集成 | B10: PASS | C10: 19/19 | D10: 0 | E10: 含 ST-102、ST-103、迁移和认证授权 | F10: execution_results/2026-07-26-current/full-validation/integration-junit.xml
A11: 前端 Lint/Build | B11: PASS | C11: 2/2 | D11: 0 | E11: ESLint + production build | F11: full-validation/03~04
A12: 确定性种子与核心 E2E | B12: PASS | C12: 19/19 | D12: 0 | E12: 种子11 + Playwright 8 | F12: acceptance/
A13: 黑盒冒烟 | B13: PASS | C13: 11/11 | D13: 0 | E13: Nginx/API真实契约 | F13: acceptance/03-smoke*.log
A14: 性能门禁 | B14: PASS | C14: 3/3 | D14: 0 | E14: 3910请求、0失败、P95达标 | F14: performance/gate-result.*
... A16: LoRA实际训练产物 | B16: BLOCKED | C16: 0/33 | D16: 33 | E16: 缺依赖与三组实际产物 | F16: full-validation/backend-full-junit.xml

Sheet 模块汇总
A1: 测试模块汇总
A3: 总用例 | B3: =COUNTA(测试用例清单!A7:A55) | C3: P0 | D3: =COUNTIF(测试用例清单!E7:E55,"P0") | E3: P1 | F3: =COUNTIF(测试用例清单!E7:E55,"P1")
A5: 模块 | B5: 关联 Epic/Story | C5: 用例数 | D5: P0 | E5: P1 | F5: 自动化与执行说明 | G5: 负责人/结果
A6: 认证、治理与资源权限 | B6: EP-01 / ST-101、103 | C6: =COUNTIF(测试用例清单!$D$7:$D$55,A6) | D6: =COUNTIFS(测试用例清单!$D$7:$D$55,A6,测试用例清单!$E$7:$E$55,"P0") | E6: =COUNTIFS(测试用例清单!$D$7:$D$55,A6,测试用例清单!$E$7:$E$55,"P1") | F6: 已有项目原生自动化证据；在发布候选基线复跑并回填结果 | G6: 未执行
A7: 知识库、文档与任务 | B7: EP-01～02 / ST-102、201、202 | C7: =COUNTIF(测试用例清单!$D$7:$D$55,A7) | D7: =COUNTIFS(测试用例清单!$D$7:$D$55,A7,测试用例清单!$E$7:$E$55,"P0") | E7: =COUNTIFS(测试用例清单!$D$7:$D$55,A7,测试用例清单!$E$7:$E$55,"P1") | F7: 已有项目原生自动化证据；在发布候选基线复跑并回填结果 | G7: 未执行
A8: 混合检索、RAG与流式协议 | B8: EP-02～03 / ST-202、301、302 | C8: =COUNTIF(测试用例清单!$D$7:$D$55,A8) | D8: =COUNTIFS(测试用例清单!$D$7:$D$55,A8,测试用例清单!$E$7:$E$55,"P0") | E8: =COUNTIFS(测试用例清单!$D$7:$D$55,A8,测试用例清单!$E$7:$E$55,"P1") | F8: 已有项目原生自动化证据；在发布候选基线复跑并回填结果 | G8: 未执行
A9: 商家口碑、点评与洞察 | B9: EP-04、06 / ST-401、402、603 | C9: =COUNTIF(测试用例清单!$D$7:$D$55,A9) | D9: =COUNTIFS(测试用例清单!$D$7:$D$55,A9,测试用例清单!$E$7:$E$55,"P0") | E9: =COUNTIFS(测试用例清单!$D$7:$D$55,A9,测试用例清单!$E$7:$E$55,"P1") | F9: 已有项目原生自动化证据；在发布候选基线复跑并回填结果 | G9: 未执行
A10: 反馈、数据集与模型治理 | B10: EP-05 / ST-501、502 | C10: =COUNTIF(测试用例清单!$D$7:$D$55,A10) | D10: =COUNTIFS(测试用例清单!$D$7:$D$55,A10,测试用例清单!$E$7:$E$55,"P0") | E10: =COUNTIFS(测试用例清单!$D$7:$D$55,A10,测试用例清单!$E$7:$E$55,"P1") | F10: 已有项目原生自动化证据；在发布候选基线复跑并回填结果 | G10: 未执行
A11: 前端路由、管理与体验 | B11: EP-06 / ST-601、602 | C11: =COUNTIF(测试用例清单!$D$7:$D$55,A11) | D11: =COUNTIFS(测试用例清单!$D$7:$D$55,A11,测试用例清单!$E$7:$E$55,"P0") | E11: =COUNTIFS(测试用例清单!$D$7:$D$55,A11,测试用例清单!$E$7:$E$55,"P1") | F11: 已有项目原生自动化证据；在发布候选基线复跑并回填结果 | G11: 未执行
A12: 部署、质量、验收与恢复 | B12: EP-07 / ST-701～703 | C12: =COUNTIF(测试用例清单!$D$7:$D$55,A12) | D12: =COUNTIFS(测试用例清单!$D$7:$D$55,A12,测试用例清单!$E$7:$E$55,"P0") | E12: =COUNTIFS(测试用例清单!$D$7:$D$55,A12,测试用例清单!$E$7:$E$55,"P1") | F12: 已有项目原生自动化证据；在发布候选基线复跑并回填结果 | G12: 未执行
A13: 合计 | C13: =SUM(C6:C12) | D13: =SUM(D6:D12) | E13: =SUM(E6:E12)

Sheet 执行说明
A1: 测试代码与执行说明
A3: 项目 | B3: 内容
A4: 代码目录 | B4: docs/测试用例文档/test_code
A5: 黑盒冒烟 | B5: python -m pytest docs/测试用例文档/test_code/test_release_candidate_smoke.py -q
A6: 列出 AUTH 证据 | B6: python docs/测试用例文档/test_code/run_project_test_cases.py AUTH --list
A7: 执行选定域 | B7: python docs/测试用例文档/test_code/run_project_test_cases.py AUTH KB RAG
A8: 校验交付一致性 | B8: python -m pytest docs/测试用例文档/test_code/test_delivery_consistency.py -q
A9: 列出全部证据 | B9: python docs/测试用例文档/test_code/run_project_test_cases.py --all --list
A10: PowerShell 入口 | B10: .\docs\测试用例文档\test_code\run_selected_cases.ps1 -Group AUTH,KB,RAG
A11: 基础地址 | B11: LOCAL_LIFE_BASE_URL，默认 http://127.0.0.1:3000
A12: 认证账号 | B12: LOCAL_LIFE_TEST_USERNAME / LOCAL_LIFE_TEST_PASSWORD
A13: 检索知识库 | B13: LOCAL_LIFE_TEST_KB_ID：当前账号有权访问的知识库 UUID
A14: 执行原则 | B14: 最终结果必须绑定发布候选 Commit；外部依赖缺失应记为阻塞或条件跳过，不得伪造通过。
... A16: 恢复演练 | B16: 使用 scripts/run_tk703_recovery.ps1；精确确认目标环境，禁止覆盖事实库。

Sheet 历史证据
A1: 既有测试与发布门禁证据
A3: 证据 | B3: 日期 | C3: 历史结果 | D3: 判定 | E3: 适用说明 | F3: 来源
A4: TK-703-01 后端测试与覆盖率 | B4: 46225 | C4: 916通过、0失败、39跳过；语句79.00%，报告口径分支74.80% | D4: 通过 | E4: 证明既有提交满足≥70%；最终 Commit 需复跑 | F4: docs/reports/2026-07-22-TK-703-01后端测试与覆盖率报告.md
A5: TK-703-02 安全专项 | B5: 46225 | C5: 专项79通过、2条件跳过；后续完整回归932通过、39跳过、0失败 | D5: 通过 | E5: 安全控制已有自动化证据 | F5: docs/reports/2026-07-22-TK-703-02安全专项验收报告.md
A6: TK-702-03 全新环境三轮 | B6: 46225 | C6: 3/3轮通过；每轮Playwright 10/10 | D6: 通过 | E6: 确定性演示链路可复演 | F6: docs/reports/2026-07-22-TK-702-03全新环境回归报告.md
A7: TK-703-04 恢复演练 | B7: 46225 | C7: 专项11通过；31张表恢复一致；索引差异0；Redis回源成功 | D7: 通过 | E7: 真实 Compose 恢复与对账证据 | F7: docs/reports/2026-07-22-TK-703-04存储对账与恢复演练报告.md
A8: TK-703-03 性能门禁 | B8: 46225 | C8: 三项0样本，P95 N/A | D8: 阻断 | E8: 必须补充目标环境真实HTTP链路样本 | F8: docs/reports/2026-07-22-TK-703-03-Locust性能门禁报告.md
A9: TK-703-05 发布门禁 | B9: 46225 | C9: GATE-703-P0-001 OPEN / BLOCKING | D9: NOT APPROVED | E9: 性能阻断关闭前禁止发布 | F9: docs/reports/2026-07-22-TK-703-05发布门禁验收记录.md
